LICENSE.txt
MANIFEST.in
README.md
requirements.txt
setup.py
fabric_utils/__init__.py
fabric_utils/server.py
fabric_utils/utils.py
fabric_utils.egg-info/PKG-INFO
fabric_utils.egg-info/SOURCES.txt
fabric_utils.egg-info/dependency_links.txt
fabric_utils.egg-info/top_level.txt
fabric_utils/django/__init__.py
fabric_utils/django/deployment.py
fabric_utils/django/db/__init__.py
fabric_utils/django/db/tasks.py
fabric_utils/django/db/mysql/__init__.py
fabric_utils/django/db/mysql/tasks.py
fabric_utils/django/server/__init__.py
fabric_utils/django/server/utils.py