Metadata-Version: 1.0
Name: fabric-utils
Version: 0.0.3
Summary: Fabric utils for deployment management
Home-page: https://github.com/dsaenztagarro/fabric-utils
Author: David Saenz Tagarro
Author-email: david.saenz.tagarro@gmail.com
License: LICENSE.txt
Keywords: fabric django apache
Platform: UNKNOWN
